setup.py
udc_mlnd_probability/Binomialdistribution.py
udc_mlnd_probability/Gaussiandistribution.py
udc_mlnd_probability/Generaldistribution.py
udc_mlnd_probability/__init__.py
udc_mlnd_probability.egg-info/PKG-INFO
udc_mlnd_probability.egg-info/SOURCES.txt
udc_mlnd_probability.egg-info/dependency_links.txt
udc_mlnd_probability.egg-info/not-zip-safe
udc_mlnd_probability.egg-info/top_level.txt