Metadata-Version: 1.0
Name: udc-mlnd-probability
Version: 0.1
Summary: Gaussian and Binomial distributions
Home-page: UNKNOWN
Author: Chukwuemeka Ezumezu
Author-email: emyfrancis2012@gmail.com
License: UNKNOWN
Platform: UNKNOWN
